odoo8_addon_shopinvader_product_rating-8.0.1.0.0.99.dev2-py3.8-nspkg.pth
odoo_addons/shopinvader_product_rating/README.rst
odoo_addons/shopinvader_product_rating/__init__.py
odoo_addons/shopinvader_product_rating/__openerp__.py
odoo_addons/shopinvader_product_rating/data/ir_export.xml
odoo_addons/shopinvader_product_rating/models/__init__.py
odoo_addons/shopinvader_product_rating/models/product.py
odoo8_addon_shopinvader_product_rating-8.0.1.0.0.99.dev2.dist-info/METADATA
odoo8_addon_shopinvader_product_rating-8.0.1.0.0.99.dev2.dist-info/WHEEL
odoo8_addon_shopinvader_product_rating-8.0.1.0.0.99.dev2.dist-info/namespace_packages.txt
odoo8_addon_shopinvader_product_rating-8.0.1.0.0.99.dev2.dist-info/top_level.txt
odoo8_addon_shopinvader_product_rating-8.0.1.0.0.99.dev2.dist-info/RECORD
